bbot_mcp/__init__.py
bbot_mcp/server.py
bbot_mcp-0.1.4.dist-info/METADATA
bbot_mcp-0.1.4.dist-info/WHEEL
bbot_mcp-0.1.4.dist-info/entry_points.txt
bbot_mcp-0.1.4.dist-info/licenses/LICENSE
bbot_mcp-0.1.4.dist-info/RECORD
