Metadata-Version: 2.4
Name: bbot-mcp
Version: 0.1.4
Summary: MCP server for BBOT security scanner
Project-URL: Homepage, https://github.com/marlinkcyber/bbot-mcp
Project-URL: Repository, https://github.com/marlinkcyber/bbot-mcp
Project-URL: Issues, https://github.com/marlinkcyber/bbot-mcp/issues
Author-email: Vlatko Kosturjak <vlatko.kosturjak@marlink.com>
License: MIT
License-File: LICENSE
Keywords: bbot,mcp,scanner,security
Classifier: Development Status :: 4 - Beta
Classifier: Intended Audience :: Developers
Classifier: License :: OSI Approved :: MIT License
Classifier: Programming Language :: Python :: 3
Classifier: Programming Language :: Python :: 3.8
Classifier: Programming Language :: Python :: 3.9
Classifier: Programming Language :: Python :: 3.10
Classifier: Programming Language :: Python :: 3.11
Classifier: Programming Language :: Python :: 3.12
Classifier: Programming Language :: Python :: 3.13
Requires-Python: >=3.8
Requires-Dist: bbot>=2.5.0
Requires-Dist: mcp>=1.12.0
